igenstrings/__init__.py
igenstrings/cli.py
igenstrings/i18n.py
igenstrings/merger.py
igenstrings/parser.py
igenstrings-1.1.0.dist-info/DESCRIPTION.rst
igenstrings-1.1.0.dist-info/entry_points.txt
igenstrings-1.1.0.dist-info/METADATA
igenstrings-1.1.0.dist-info/metadata.json
igenstrings-1.1.0.dist-info/RECORD
igenstrings-1.1.0.dist-info/top_level.txt
igenstrings-1.1.0.dist-info/WHEEL
