Metadata-Version: 2.0
Name: igenstrings
Version: 1.1.0
Summary: Enhance the genstrings command by adding merging capabilities
Home-page: https://github.com/dulaccc/igenstrings
Author: Pierre Dulac
Author-email: pierre@dulaccc.me
License: MIT
Platform: UNKNOWN
Classifier: Development Status :: 4 - Beta
Classifier: Environment :: Console
Classifier: Intended Audience :: Developers
Classifier: License :: OSI Approved :: MIT License
Classifier: Natural Language :: English
Classifier: Operating System :: MacOS :: MacOS X
Classifier: Programming Language :: Python :: 2
Classifier: Programming Language :: Python :: 2.7
Classifier: Programming Language :: Python :: 3
Classifier: Programming Language :: Python :: 3.3
Classifier: Programming Language :: Python :: 3.4
Classifier: Programming Language :: Python :: 3.5
Requires-Dist: click (==6.6)
Requires-Dist: chardet (==2.3.0)
